Workbook

Sheet READ ME
A1: RESOLV CORPORATION:- Performance Data File
A2: Customer Intelligence & Performance Management - Q1 2026 Data Template
A4: PURPOSE
A5: This workbook contains all placeholder data used in the Resolv Corporation Performance Report (Q1 2026).
A6: It is structured as a live data template. Replace the placeholder values with real data from your CRM, ERP, and survey systems each quarter.
A8: SHEET GUIDE
A9: Sheet 1 - Branding Metrics | NPS, recognition, quality, delivery, CSAT, quarterly trend Q1 2025 to Q1 2026
A10: Sheet 2 - Rejection Management | Rejection trend, root cause breakdown, sample program effectiveness
A11: Sheet 3 - Competitive Pricing | Challenge log, price gap analysis, retention levers, competitor intel
A12: Sheet 4 - KPI Summary | Top-line KPIs pulled from the three pillar sheets via formulas
A14: HOW TO USE
A15: 1. Blue-highlighted cells = placeholder data. Replace these with real figures from your systems.
... A28: Prepared by: Strategy & Sales Analytics, Resolv Corporation | Reporting Period: Q1 2026

Sheet 1 - Branding Metrics
A1: SHEET 1:- BRANDING METRICS
A2: Source: Quarterly Customer Satisfaction Survey | Update Frequency: Quarterly | Blue cells = placeholder data to replace with real survey results
A4: TABLE 1A:- Brand Performance Scorecard (Quarterly Trend)
A5: Metric | B5: Q1 2025 | C5: Q2 2025 | D5: Q3 2025 | E5: Q4 2025 | F5: Q1 2026 (Actual) | G5: Q1 2026 Target | H5: vs Target
A6: Net Promoter Score (NPS) | B6: 52 | C6: 55 | D6: 58 | E6: 61 | F6: 68 | G6: 65 | H6: =IF(F6>=G6,"✓ Above Target","✗ Below Target") -> ✓ Above Target
A7: Product Name Recognition (%) | B7: 0.65 | C7: 0.68 | D7: 0.71 | E7: 0.74 | F7: 0.79 | G7: 0.75 | H7: =IF(F7>=G7,"✓ Above Target","✗ Below Target") -> ✓ Above Target
A8: Quality Consistency Rating (/5) | B8: 3.9 | C8: 4 | D8: 4.1 | E8: 4.3 | F8: 4.5 | G8: 4.4 | H8: =IF(F8>=G8,"✓ Above Target","✗ Below Target") -> ✓ Above Target
A9: On-Time Delivery Rate (%) | B9: 0.88 | C9: 0.89 | D9: 0.91 | E9: 0.93 | F9: 0.96 | G9: 0.95 | H9: =IF(F9>=G9,"✓ Above Target","✗ Below Target") -> ✓ Above Target
A10: Customer Satisfaction (CSAT %) | B10: 0.79 | C10: 0.81 | D10: 0.82 | E10: 0.85 | F10: 0.88 | G10: 0.86 | H10: =IF(F10>=G10,"✓ Above Target","✗ Below Target") -> ✓ Above Target
A11: Brand Recall in Target Segment (%) | B11: 0.38 | C11: 0.41 | D11: 0.44 | E11: 0.49 | F11: 0.55 | G11: 0.52 | H11: =IF(F11>=G11,"✓ Above Target","✗ Below Target") -> ✓ Above Target
A13: TABLE 1B:- NPS Score by Customer Tier (Q1 2026)
A14: Customer Tier | B14: Respondents | C14: NPS Score | D14: QoQ Change
A15: Tier 1 - Annual Blanket (>$500K) | B15: 38 | C15: 81 | D15: +9
A16: Tier 2 - Confirmed Orders ($100K–$500K) | B16: 52 | C16: 71 | D16: +7
A17: Tier 3 - Spot Orders (<$100K) | B17: 22 | C17: 48 | D17: +4
A18: Overall (All Tiers) | B18: =SUM(B15:B17) -> 112 | C18: =SUMPRODUCT(B15:B17,C15:C17)/SUM(B15:B17) -> 69.875 | D18: +7
A20: NOTE: Replace all blue-highlighted values with actual survey results each quarter. Weighted NPS in 'Overall' row is auto-calculated via formula.

Sheet 2 - Rejection Management
A1: SHEET 2:- CUSTOMER REJECTION MANAGEMENT & SAMPLE PROGRAM
A2: Source: ERP / Order Management System (rejection records) + Operations Sample Dispatch Log | Update Frequency: Quarterly
A4: TABLE 2A:- Rejection Trend by Quarter
A5: Quarter | B5: Total Shipments | C5: Rejections | D5: Rejection Rate | E5: Samples Sent | F5: Rejections Prevented | G5: Est. Cost/Rejection ($) | H5: Est. Cost Saved ($)
A6: Q1 2025 | B6: 312 | C6: 18 | D6: =C6/B6 -> 0.057692308 | E6: 41 | F6: 9 | G6: 4200 | H6: =F6*G6 -> 37800
A7: Q2 2025 | B7: 329 | C7: 14 | D7: =C7/B7 -> 0.042553191 | E7: 58 | F7: 13 | G7: 4200 | H7: =F7*G7 -> 54600
A8: Q3 2025 | B8: 341 | C8: 10 | D8: =C8/B8 -> 0.029325513 | E8: 74 | F8: 17 | G8: 4200 | H8: =F8*G8 -> 71400
A9: Q4 2025 | B9: 358 | C9: 8 | D9: =C9/B9 -> 0.022346369 | E9: 89 | F9: 20 | G9: 4200 | H9: =F9*G9 -> 84000
A10: Q1 2026 | B10: 372 | C10: 7 | D10: =C10/B10 -> 0.018817204 | E10: 104 | F10: 23 | G10: 4200 | H10: =F10*G10 -> 96600
A11: TOTAL / AVERAGE | B11: =SUM(B6:B10) -> 1712 | C11: =SUM(C6:C10) -> 57 | D11: =C11/B11 -> 0.033294393 | E11: =SUM(E6:E10) -> 366 | F11: =SUM(F6:F10) -> 82 | G11: =AVERAGE(G6:G10) -> 4200 | H11: =SUM(H6:H10) -> 344400
A13: TABLE 2B:- Rejection Root Cause Analysis (Q1 2026)
A14: Root Cause | B14: Rejection Count | C14: Share of Total | D14: Avg Resolution (Days) | E14: Prevention Method | F14: Status
A15: Application mismatch (customer-side) | B15: 3 | C15: =B15/7 -> 0.42857143 | D15: 6 | E15: Pre-shipment sample approval | F15: Preventable — sample program
A16: Specification deviation (minor) | B16: 2 | C16: =B16/7 -> 0.28571429 | D16: 4 | E16: QC process update / re-inspection | F16: Addressed — process updated
A17: Packaging / transit damage | B17: 1 | C17: =B17/7 -> 0.14285714 | D17: 3 | E17: Carrier claim + repack review | F17: In progress — carrier claim filed
A18: Customer requirement change | B18: 1 | C18: =B18/7 -> 0.14285714 | D18: 8 | E18: Order review protocol | F18: Under review
A20: TABLE 2C:- Sample Program Effectiveness (Q1 2026)
A21: Sample Type | B21: Samples Dispatched | C21: Approvals Received | D21: Approval Rate | E21: Avg Time to Approval | F21: Notes
A22: Pre-Shipment Sample | B22: 61 | C22: 58 | D22: =C22/B22 -> 0.95081967 | E22: 4.2 business days | F22: Most effective, eliminates application mismatch risk
A23: Co-Shipment Sample | B23: 43 | C23: 40 | D23: =C23/B23 -> 0.93023256 | E23: Concurrent w/ delivery | F23: High approval; reference standard for any post-delivery dispute
A24: New Customer Trial Sample | B24: 18 | C24: 14 | D24: =C24/B24 -> 0.77777778 | E24: 7.1 business days | F24: Lowest approval rate, recommend dedicated tech support at onboarding
A25: Total / Weighted Average | B25: =SUM(B22:B24) -> 122 | C25: =SUM(C22:C24) -> 112 | D25: =C25/B25 -> 0.91803279
A27: NOTE: Total rejections for share calculation in Table 2B is hardcoded as 7 (Q1 2026 total). Update if actual figure differs. Blue cells = placeholder inputs from ERP/ops log.

Sheet 3 - Competitive Pricing
A1: SHEET 3:- COMPETITIVE PRICING INTELLIGENCE & CUSTOMER RETENTION
A2: Source: CRM Competitive Quote Log (sales team field entries) | Update Frequency: Quarterly | See Recommendation R1 for logging protocol
A4: TABLE 3A:- Competitive Challenge Summary (Q1 2026)
A5: Outcome Category | B5: Account Count | C5: % of Challenged Accounts | D5: Est. Annual Revenue ($) | E5: Notes
A6: Retained:- Price Match Applied | B6: 22 | C6: =B6/B9 -> 0.70967742 | D6: 1060000 | E6: Volume/blanket discount or price match deployed
A7: Retained:- Value / Quality Argument | B7: 5 | C7: =B7/B9 -> 0.16129032 | D7: 240000 | E7: Customer convinced by quality / sample program history
A8: Lost to Competitor | B8: 4 | C8: =B8/B9 -> 0.12903226 | D8: 620000 | E8: Price gap too large OR intelligence gap — no advance response
A9: Total Challenged Accounts | B9: 31 | C9: 1 | D9: 1920000 | E9: 8.3% of active account base
A11: TABLE 3B:- Competitive Price Gap Log (Q1 2026, Sampled Events)
A12: Customer Tier | B12: Competitor Price ($/unit) | C12: Resolv Price ($/unit) | D12: Price Gap % | E12: Retention Lever Applied | F12: Outcome | G12: Revenue at Stake ($)
A13: Tier 1:- Annual Blanket | B13: 12.4 | C13: 12.8 | D13: =(C13-B13)/B13 -> 0.032258065 | E13: Volume discount applied | F13: Retained | G13: 520000
A14: Tier 1:- Annual Blanket | B14: 11.9 | C14: 12.6 | D14: =(C14-B14)/B14 -> 0.058823529 | E14: Bulk packaging + price match | F14: Retained | G14: 610000
A15: Tier 2:- Confirmed Orders | B15: 14.2 | C15: 14.5 | D15: =(C15-B15)/B15 -> 0.021126761 | E15: Held price — quality argument deployed | F15: Retained | G15: 180000
A16: Tier 2:- Confirmed Orders | B16: 13.8 | C16: 15.1 | D16: =(C16-B16)/B16 -> 0.094202899 | E16: Partial match offered — declined | F16: Lost | G16: 210000
A17: Tier 3:- Spot Orders | B17: 16 | C17: 16.4 | D17: =(C17-B17)/B17 -> 0.025 | E17: No adjustment — margin floor | F17: Retained | G17: 55000
A18: Tier 3:- Spot Orders | B18: 15.2 | C18: 16.9 | D18: =(C18-B18)/B18 -> 0.11184211 | E18: Cannot match at spot volume | F18: Lost | G18: 72000
A20: TABLE 3C:- Retention Lever Effectiveness (Q1 2026)
A21: Retention Lever | B21: Times Deployed | C21: Successes | D21: Success Rate | E21: Avg Revenue Retained ($)
A22: Volume / Annual Blanket Discount | B22: 11 | C22: 10 | D22: =C22/B22 -> 0.90909091 | E22: 48200
A23: Bulk Packaging Credit | B23: 8 | C23: 7 | D23: =C23/B23 -> 0.875 | E23: 22700
A24: Confirmed Order Lock-in Pricing | B24: 6 | C24: 5 | D24: =C24/B24 -> 0.83333333 | E24: 31500
A25: Quality / Sample Value Argument | B25: 5 | C25: 4 | D25: =C25/B25 -> 0.8 | E25: 18900
A26: Partial Price Match | B26: 4 | C26: 2 | D26: =C26/B26 -> 0.5 | E26: 9400
A27: No Action (price held at margin floor) | B27: 3 | C27: 1 | D27: =C27/B27 -> 0.33333333 | E27: 4100
A29: TABLE 3D:- Competitor Intelligence Summary (Q1 2026)
A30: Competitor | B30: Q1 2026 Challenges | C30: Avg Price Undercut (%) | D30: Resolv Win Rate (%) | E30: Identified Competitive Weakness
A31: Competitor A | B31: 14 | C31: 0.041 | D31: 0.79 | E31: Inconsistent product quality; no pre-shipment sample program offered
A32: Competitor B | B32: 9 | C32: 0.068 | D32: 0.67 | E32: Long and unreliable lead times; limited customer service responsiveness
A33: Competitor C | B33: 5 | C33: 0.032 | D33: 0.8 | E33: Narrow product range; limited sector coverage outside core market
A34: Other / Unknown | B34: 3 | C34: 0.095 | D34: 0.33 | E34: Likely offshore / unvetted supplier; no established quality track record
A37: NOTE: Competitive quote data depends on sales team field reporting. Gaps in coverage are expected until CRM logging protocol (Recommendation R1) is fully implemented. Blue cells = placeholder inputs.

Sheet 4 - KPI Summary
A1: SHEET 4:- EXECUTIVE KPI SUMMARY DASHBOARD
A2: All cells in this sheet pull data directly from Sheets 1–3 via formula. Update source data in those sheets and this dashboard auto-refreshes.
A4: PILLAR I:- BRANDING METRICS (Q1 2026)
A5: KPI | B5: Q1 2026 Actual | C5: Target / Benchmark | D5: Status | E5: Source Sheet
A6: Net Promoter Score (NPS) | B6: ='1 - Branding Metrics'!F5 -> Q1 2026 (Actual) | C6: 65+ | D6: =IF(B6<>"","✓ See source sheet","No data") -> ✓ See source sheet | E6: Sheet 3 - Pricing
A7: Product Name Recognition | B7: ='1 - Branding Metrics'!F6 -> 68 | C7: 75% | D7: =IF(B7<>"","✓ See source sheet","No data") -> ✓ See source sheet | E7: Sheet 3 - Pricing
A8: Quality Consistency Rating (/5) | B8: ='1 - Branding Metrics'!F7 -> 0.79 | C8: 4.4/5 | D8: =IF(B8<>"","✓ See source sheet","No data") -> ✓ See source sheet | E8: Sheet 3 - Pricing
A9: On-Time Delivery Rate | B9: ='1 - Branding Metrics'!F8 -> 4.5 | C9: 95% | D9: =IF(B9<>"","✓ See source sheet","No data") -> ✓ See source sheet | E9: Sheet 3 - Pricing
A10: Customer Satisfaction (CSAT) | B10: ='1 - Branding Metrics'!F9 -> 0.96 | C10: 86% | D10: =IF(B10<>"","✓ See source sheet","No data") -> ✓ See source sheet | E10: Sheet 3 - Pricing
A11: Brand Recall in Target Segment | B11: ='1 - Branding Metrics'!F10 -> 0.88 | C11: 52% | D11: =IF(B11<>"","✓ See source sheet","No data") -> ✓ See source sheet | E11: Sheet 3 - Pricing
A13: PILLAR II:- REJECTION MANAGEMENT (Q1 2026)
A14: KPI | B14: Q1 2026 Actual | C14: Target / Benchmark | D14: Status | E14: Source Sheet
A15: Total Shipments | B15: ='2 - Rejection Management'!B10 -> 372 | C15: — | D15: =IF(B15<>"","✓ See source sheet","No data") -> ✓ See source sheet | E15: Sheet 2 - Rejections
A16: Total Rejections | B16: ='2 - Rejection Management'!C10 -> 7 | C16: — | D16: =IF(B16<>"","✓ See source sheet","No data") -> ✓ See source sheet | E16: Sheet 2 - Rejections
A17: Rejection Rate | B17: ='2 - Rejection Management'!D10 -> 0.018817204 | C17: <2.0% | D17: =IF(B17<>"","✓ See source sheet","No data") -> ✓ See source sheet | E17: Sheet 2 -0 Rejections
A18: Total Samples Dispatched | B18: ='2 - Rejection Management'!E10 -> 104 | C18: — | D18: =IF(B18<>"","✓ See source sheet","No data") -> ✓ See source sheet | E18: Sheet 2 - Rejections
A19: Rejections Prevented (Samples) | B19: ='2 - Rejection Management'!F10 -> 23 | C19: — | D19: =IF(B19<>"","✓ See source sheet","No data") -> ✓ See source sheet | E19: Sheet 2 - Rejections
A20: Estimated Cost Saved ($) | B20: ='2 - Rejection Management'!H10 -> 96600 | C20: — | D20: =IF(B20<>"","✓ See source sheet","No data") -> ✓ See source sheet | E20: Sheet 2 - Rejections
A22: PILLAR III:- COMPETITIVE PRICING (Q1 2026)
A23: KPI | B23: Q1 2026 Actual | C23: Target / Benchmark | D23: Status | E23: Source Sheet
A24: Competitive Challenges (Total) | B24: ='3 - Competitive Pricing'!B8 -> 4 | C24: — | D24: =IF(B24<>"","✓ See source sheet","No data") -> ✓ See source sheet | E24: Sheet 3 - Pricing
A25: Accounts Retained - Price Match | B25: ='3 - Competitive Pricing'!B6 -> 22 | C25: — | D25: =IF(B25<>"","✓ See source sheet","No data") -> ✓ See source sheet | E25: Sheet 3 - Pricing
A26: Accounts Retained - Value Argument | B26: ='3 - Competitive Pricing'!B7 -> 5 | C26: — | D26: =IF(B26<>"","✓ See source sheet","No data") -> ✓ See source sheet | E26: Sheet 3 - Pricing
A27: Accounts Lost to Competitor | B27: ='3 - Competitive Pricing'!B9 -> 31 | C27: — | D27: =IF(B27<>"","✓ See source sheet","No data") -> ✓ See source sheet | E27: Sheet 3 - Pricing
A28: Overall Price Challenge Win Rate | B28: =('3 - Competitive Pricing'!B6+'3 - Competitive Pricing'!B7)/'3 - Competitive Pricing'!B8 -> 6.75 | C28: 87% | D28: =IF(B28<>"","✓ See source sheet","No data") -> ✓ See source sheet | E28: Sheet 3 - Pricing
A29: Revenue at Risk - Lost Accounts ($) | B29: ='3 - Competitive Pricing'!D9 -> 1920000 | C29: — | D29: =IF(B29<>"","✓ See source sheet","No data") -> ✓ See source sheet | E29: Sheet 3 - Pricing
